{
   "test": "See hero, kill hero",
   "title":"How doomed are you?",
   "headerstart":"Unofficail League of Legends application of ",
   "headermid":"How doomed are you?",
   "headerend":"by C4",
   "waiting":"Your DOOM is calculating, please wait.",
   "inputerror":"Your inputs are wrong!",
   "name":"Your Summoner Name: ",
   "region":"Your Region: ",
   "remember":"Remember me",
   "inputbutton":"Match me with retards!",
   "doomtitle":"Your faith is sealed. Prepare for your DOOM...",
   "teamoverview":"Team overview",
   "ally":"Ally",
   "enemy":"Enemy",
   "df":"DF",
   "kda":"KDA",
   "winrate":"Winrate",
   "gold":"Gold",
   "cs":"CS",
   "turret":"Turret",
   "doom":"Doom",
   "total":"Total",
   "playeroverview":"Players overview",
   "player":"Player",
   "win":"Win",
   "lost":"Lost",
   "kill":"Kill",
   "death":"Death",
   "assist":"Assist",
   "doombutton":"Match me with retards! Again...",
   "level0":"Your doom lvl is over 9000!",
   "level1":"Did you sacrificed a kitty today?",
   "level2":"Surrend @ 20...",
   "level3":"GG",
   "level4":"You can forget your food in the microwave.",
   "level5":"You have to bait them and outsmart them.",
   "level6":"OK",
   "level7":"Tons of damage!",
   "level8":"You see hero, you kill hero!",
   "level9":"If you want to play with me, you better be sure you know the game.",
   "level10":"Blessed by the light!",
   "errormessage":"Some error occurred, please try again!",
   "errorbutton":"OK"
}